autoapi/__init__.py
autoapi/admin.py
autoapi/apps.py
autoapi/dynamic.py
autoapi/models.py
autoapi/pagination.py
autoapi/permissions.py
autoapi/router.py
autoapi/tests.py
autoapi/urls.py
autoapi/views.py
autoapi/migrations/0001_initial.py
autoapi/migrations/__init__.py
django_ant_autoapi-0.1.4.dist-info/licenses/LICENSE
django_ant_autoapi-0.1.4.dist-info/METADATA
django_ant_autoapi-0.1.4.dist-info/WHEEL
django_ant_autoapi-0.1.4.dist-info/top_level.txt
django_ant_autoapi-0.1.4.dist-info/RECORD
