Metadata-Version: 2.4
Name: django-ant-autoapi
Version: 0.1.4
Summary: Auto-generate CRUD API views for Django models.
Author-email: daxu <xuh@daxu.cc>
License: MIT License
Project-URL: Homepage, https://github.com/buslink/Django-Ant-Admin
Project-URL: Documentation, https://github.com/buslink/Django-Ant-Admin#readme
Project-URL: Source, https://github.com/buslink/Django-Ant-Admin
Project-URL: Issues, https://github.com/buslink/Django-Ant-Admin/issues
Requires-Python: >=3.8
License-File: LICENSE
Requires-Dist: Django>=4.0
Requires-Dist: djangorestframework>=3.14
Dynamic: license-file
